Metadata-Version: 2.1
Name: probality-distributions
Version: 1.1
Summary: Gaussian and Binomial distributions formulas
Home-page: UNKNOWN
Author: Rodolfo Frois
Author-email: froisrodolfo@gmail.com
License: UNKNOWN
Platform: UNKNOWN
